espn_api_orm/__init__.py
espn_api_orm/consts.py
espn_api_orm/athlete/api.py
espn_api_orm/athlete/schema.py
espn_api_orm/calendar/__init__.py
espn_api_orm/calendar/api.py
espn_api_orm/calendar/schema.py
espn_api_orm/event/__init__.py
espn_api_orm/event/api.py
espn_api_orm/event/schema.py
espn_api_orm/generic/__init__.py
espn_api_orm/generic/api.py
espn_api_orm/generic/schema.py
espn_api_orm/league/__init__.py
espn_api_orm/league/api.py
espn_api_orm/league/schema.py
espn_api_orm/scoreboard/__init__.py
espn_api_orm/scoreboard/api.py
espn_api_orm/scoreboard/schema.py
espn_api_orm/season/__init__.py
espn_api_orm/season/api.py
espn_api_orm/season/schema.py
espn_api_orm/sport/__init__.py
espn_api_orm/sport/api.py
espn_api_orm/sport/schema.py
espn_api_orm/team/__init__.py
espn_api_orm/team/api.py
espn_api_orm/team/schema.py
espn_api_orm/venue/__init__.py
espn_api_orm/venue/api.py
espn_api_orm/venue/schema.py
espn_api_orm-0.0.9.dist-info/licenses/LICENSE
espn_api_orm-0.0.9.dist-info/METADATA
espn_api_orm-0.0.9.dist-info/WHEEL
espn_api_orm-0.0.9.dist-info/top_level.txt
espn_api_orm-0.0.9.dist-info/RECORD
