Metadata-Version: 2.4
Name: espn-api-orm
Version: 0.0.9
Summary: A Python interface for the ESPN API
Author-email: TheEdgePredictor <theedgepredictor@gmail.com>, Charlie Sergeant <charlesdsgt@gmail.com>
Project-URL: Repository, https://github.com/theedgepredictor/espn-api-orm
Project-URL: Homepage, https://github.com/theedgepredictor/espn-api-orm
Project-URL: Issues, https://github.com/theedgepredictor/espn-api-orm/issues
Keywords: data science,ORM,sports
Classifier: Programming Language :: Python :: 3
Classifier: License :: OSI Approved :: MIT License
Classifier: Operating System :: OS Independent
Requires-Python: >=3.8
License-File: LICENSE
Requires-Dist: pydantic>2.0.0
Requires-Dist: requests>=2.31.0
Provides-Extra: test
Requires-Dist: pytest>7.0.0; extra == "test"
Dynamic: license-file
